fastapi_authtools/__init__.py
fastapi_authtools/backend.py
fastapi_authtools/exceptions.py
fastapi_authtools/middleware.py
fastapi_authtools/token.py
fastapi_authtools/user.py
fastapi_authtools-1.0.dist-info/LICENSE
fastapi_authtools-1.0.dist-info/METADATA
fastapi_authtools-1.0.dist-info/WHEEL
fastapi_authtools-1.0.dist-info/top_level.txt
fastapi_authtools-1.0.dist-info/RECORD
