Metadata-Version: 2.1
Name: fastapi-authtools
Version: 1.0
Summary: A small example package
Home-page: https://github.com/michael7nightinglae/fastapi_authtools
Author: Michael Nightingale
Author-email: Michael Nightingale <suslanchikmopl@gmail.com>
License: MIT
Project-URL: Homepage, https://github.com/michael7nightinglae/fastapi_authtools
Project-URL: Bug Tracker, https://github.com/michael7nightinglae/fastapi_authtools/issues
Classifier: Programming Language :: Python :: 3
Classifier: License :: OSI Approved :: MIT License
Classifier: Operating System :: OS Independent
Requires-Python: >=3.10
License-File: LICENSE
Requires-Dist: fastapi
Requires-Dist: python-jose
